Metadata-Version: 2.1
Name: kill-thread
Version: 0.0.1
Summary: 只有一个功能，杀死线程！
Home-page: https://github.com/JingheLee/KillThread.git
Author: Jinghe Lee
Author-email: jinghe_lee@163.com
License: UNKNOWN
Platform: UNKNOWN
License-File: LICENSE
